sphinx_ai_assistant/__init__.py
sphinx_ai_assistant/static/__init__.py
sphinx_ai_assistant/static/ai-assistant.css
sphinx_ai_assistant/static/ai-assistant.js
sphinx_ai_assistant/static/ai-tools.svg
sphinx_ai_assistant/static/arrow-down.svg
sphinx_ai_assistant/static/chatgpt.svg
sphinx_ai_assistant/static/checked.svg
sphinx_ai_assistant/static/claude.svg
sphinx_ai_assistant/static/comment-discussion.svg
sphinx_ai_assistant/static/copy-to-clipboard.svg
sphinx_ai_assistant/static/markdown.svg
sphinx_ai_assistant/static/vscode.svg
sphinx_ai_assistant-0.1.2.dist-info/licenses/LICENSE
sphinx_ai_assistant-0.1.2.dist-info/METADATA
sphinx_ai_assistant-0.1.2.dist-info/WHEEL
sphinx_ai_assistant-0.1.2.dist-info/top_level.txt
sphinx_ai_assistant-0.1.2.dist-info/RECORD
