Metadata-Version: 2.4
Name: sphinx-ai-assistant
Version: 0.1.2
Summary: A Sphinx extension that adds AI assistant features to documentation pages
Author: Mladen Zagorac
License-Expression: MIT
Project-URL: download, https://pypi.org/project/sphinx-ai-assistant/
Project-URL: source, https://github.com/mlazag/sphinx-ai-assistant
Project-URL: changelog, https://github.com/mlazag/sphinx-ai-assistant/blob/master/CHANGELOG.md
Project-URL: Homepage, https://github.com/mlazag/sphinx-ai-assistant
Project-URL: Repository, https://github.com/mlazag/sphinx-ai-assistant
Project-URL: Issues, https://github.com/mlazag/sphinx-ai-assistant/issues
Keywords: sphinx,documentation,ai,mcp,markdown
Classifier: Development Status :: 3 - Alpha
Classifier: Framework :: Sphinx :: Extension
Classifier: Intended Audience :: Developers
Classifier: Programming Language :: Python :: 3
Classifier: Programming Language :: Python :: 3.8
Classifier: Programming Language :: Python :: 3.9
Classifier: Programming Language :: Python :: 3.10
Classifier: Programming Language :: Python :: 3.11
Classifier: Programming Language :: Python :: 3.12
Classifier: Topic :: Documentation :: Sphinx
Classifier: Topic :: Software Development :: Documentation
Requires-Python: >=3.8
License-File: LICENSE
Requires-Dist: sphinx
Requires-Dist: beautifulsoup4
Requires-Dist: markdownify
Dynamic: license-file
